DataBERT_classifier/DataBERT_pipeline.py
DataBERT_classifier/__init__.py
databert-0.5.0.dist-info/LICENSE
databert-0.5.0.dist-info/METADATA
databert-0.5.0.dist-info/WHEEL
databert-0.5.0.dist-info/top_level.txt
databert-0.5.0.dist-info/RECORD
