Metadata-Version: 2.1
Name: databert
Version: 0.5.0
Summary: BERT Classifier for text classification
Home-page: https://github.com/avsolatorio/data-use/tree/main/scripts/DataBERT
Author: James Liounis
Author-email: liounisjames@gmail.com
License: MIT
Requires-Python: >=3.6
License-File: LICENSE
Requires-Dist: torch
Requires-Dist: transformers
Requires-Dist: numpy
Requires-Dist: scikit-learn
Requires-Dist: huggingface-hub
Requires-Dist: databert
